rangel/__init__.py
rangel/collection.py
rangel/util/__init__.py
rangel/util/logic.py
rangel/util/rasterize.py
rangel-0.0.8.dist-info/LICENSE.rst
rangel-0.0.8.dist-info/METADATA
rangel-0.0.8.dist-info/WHEEL
rangel-0.0.8.dist-info/top_level.txt
rangel-0.0.8.dist-info/RECORD
