Metadata-Version: 2.1
Name: rangel
Version: 0.0.8
Summary: Range data manipulations and operations
Author-email: Tariq Shihadah <tariq.shihadah@gmail.com>
License: MIT License
Project-URL: repository, https://github.com/tariqshihadah/linref
Keywords: python,range,numeric,interval,linear
Classifier: Development Status :: 1 - Planning
Classifier: Intended Audience :: Developers
Classifier: Programming Language :: Python :: 3
Classifier: License :: OSI Approved :: MIT License
Classifier: Operating System :: Unix
Classifier: Operating System :: MacOS :: MacOS X
Classifier: Operating System :: Microsoft :: Windows
Requires-Python: >=3.8
License-File: LICENSE.rst
Requires-Dist: numpy
Requires-Dist: matplotlib
Requires-Dist: scipy
